.DS_Store
networkdays/__init__.py
networkdays/__main__.py
networkdays/networkdays.py
tests/__init__.py
tests/command_line_tests.py
tests/test_jobschedule.py
tests/test_networkdays.py
python_networkdays-1.1.dist-info/AUTHORS.rst
python_networkdays-1.1.dist-info/LICENSE
python_networkdays-1.1.dist-info/METADATA
python_networkdays-1.1.dist-info/WHEEL
python_networkdays-1.1.dist-info/top_level.txt
python_networkdays-1.1.dist-info/RECORD
