Metadata-Version: 2.1
Name: python-networkdays
Version: 1.1
Summary: Business days (workdays) between two date, like `NetworkDays` function used on spreadsheets and more.
Home-page: https://github.com/cadu-leite/networkdays
Author: Carlos Leite
Author-email: caduado@gmail.com
License: UNKNOWN
Keywords: workdays,business day,networkdays,diasuteis,calendar,days,schedule,excel,feriados,holidays
Platform: UNKNOWN
Classifier: Development Status :: 5 - Production/Stable
Classifier: Environment :: Console
Classifier: Environment :: Web Environment
Classifier: Intended Audience :: Developers
Classifier: Intended Audience :: Legal Industry
Classifier: Intended Audience :: End Users/Desktop
Classifier: Intended Audience :: Manufacturing
Classifier: Intended Audience :: Customer Service
Classifier: License :: OSI Approved :: BSD License
Classifier: Operating System :: OS Independent
Classifier: Programming Language :: Python :: 3 :: Only
Classifier: Programming Language :: Python :: Implementation :: CPython
Classifier: Topic :: Office/Business 
Classifier: Topic :: Software Development
Classifier: Topic :: Utilities
Requires-Python: >=3.
